link/__init__.py
link/utils/__init__.py
link/utils/filter.py
link/utils/grammar.py
link/utils/log.py
link/utils/test/__init__.py
link/utils/test/filter.py
link/utils/test/grammar.py
link/utils/test/log.py
link.utils-2.0.dist-info/DESCRIPTION.rst
link.utils-2.0.dist-info/METADATA
link.utils-2.0.dist-info/RECORD
link.utils-2.0.dist-info/WHEEL
link.utils-2.0.dist-info/metadata.json
link.utils-2.0.dist-info/top_level.txt
