Metadata-Version: 2.0
Name: link.utils
Version: 2.0
Summary: Link utilities
Home-page: https://github.com/linkdd/link.utils
Author: David Delassus
Author-email: david.jose.delassus@gmail.com
License: MIT
Keywords: link utils
Platform: UNKNOWN
Classifier: Development Status :: 5 - Production/Stable
Classifier: License :: OSI Approved :: MIT License
Classifier: Operating System :: OS Independent
Classifier: Topic :: Utilities
Classifier: Topic :: Software Development :: Libraries :: Python Modules
Classifier: Intended Audience :: Developers
Classifier: Programming Language :: Python
Classifier: Programming Language :: Python :: 2.7
Classifier: Programming Language :: Python :: 3
Classifier: Programming Language :: Python :: 3.4
Classifier: Programming Language :: Python :: 3.5
Classifier: Programming Language :: Python :: Implementation :: CPython
Requires-Dist: b3j0f.conf (>=0.3.19)
Requires-Dist: grako (>=3.16.0)
Requires-Dist: six (>=1.10.0)
